dcrb/__init__.py
dcrb/dcrb.exe
dcrb/launcher.py
dcrb-4.0.0.dist-info/METADATA
dcrb-4.0.0.dist-info/WHEEL
dcrb-4.0.0.dist-info/entry_points.txt
dcrb-4.0.0.dist-info/top_level.txt
dcrb-4.0.0.dist-info/RECORD
