Metadata-Version: 2.4
Name: dcrb
Version: 4.0.0
Summary: Discord Remote Bot
Classifier: Programming Language :: Python :: 3
Classifier: Operating System :: Microsoft :: Windows
Requires-Python: >=3.6
Dynamic: classifier
Dynamic: requires-python
Dynamic: summary
